MANIFEST.in
setup.py
Products/__init__.py
Products.Silva.egg-info/PKG-INFO
Products.Silva.egg-info/SOURCES.txt
Products.Silva.egg-info/dependency_links.txt
Products.Silva.egg-info/namespace_packages.txt
Products.Silva.egg-info/not-zip-safe
Products.Silva.egg-info/requires.txt
Products.Silva.egg-info/top_level.txt
Products/Silva/Asset.py
Products/Silva/ContainerPolicy.py
Products/Silva/Content.py
Products/Silva/EmailMessageService.py
Products/Silva/ExtensionRegistry.py
Products/Silva/ExtensionService.py
Products/Silva/HISTORY.txt
Products/Silva/Link.py
Products/Silva/Membership.py
Products/Silva/MimetypeRegistry.py
Products/Silva/Publishable.py
Products/Silva/QuotaObject.py
Products/Silva/README.txt
Products/Silva/Root.py
Products/Silva/SilvaObject.py
Products/Silva/SilvaPermissions.py
Products/Silva/SimpleMembership.py
Products/Silva/UnicodeSplitter.py
Products/Silva/Version.py
Products/Silva/Versioning.py
Products/Silva/__init__.py
Products/Silva/cataloging.py
Products/Silva/characters.py
Products/Silva/configure.zcml
Products/Silva/emailnotifications.py
Products/Silva/ftesting.py
Products/Silva/ftesting.zcml
Products/Silva/helpers.py
Products/Silva/icon.py
Products/Silva/install.py
Products/Silva/mail.py
Products/Silva/mangle.py
Products/Silva/roleinfo.py
Products/Silva/testing.py
Products/Silva/tocfilter.py
Products/Silva/Asset_templates/assetpath.cpt
Products/Silva/Asset_templates/assetsize.cpt
Products/Silva/AutoTOC/__init__.py
Products/Silva/AutoTOC/content.py
Products/Silva/AutoTOC/rendering.py
Products/Silva/AutoTOC/views.py
Products/Silva/AutoTOC/views_templates/autotocview.pt
Products/Silva/ExtensionService_templates/configureextensions.cpt
Products/Silva/ExtensionService_templates/manageextensions.pt
Products/Silva/File/__init__.py
Products/Silva/File/content.py
Products/Silva/File/converters.py
Products/Silva/File/mimetypes.py
Products/Silva/File/service.py
Products/Silva/File/smi.py
Products/Silva/File/views.py
Products/Silva/File/smi_templates/infoportlet.cpt
Products/Silva/Folder/__init__.py
Products/Silva/Folder/addables.py
Products/Silva/Folder/content.py
Products/Silva/Folder/feeds.py
Products/Silva/Folder/management.py
Products/Silva/Folder/order.py
Products/Silva/Folder/tree.py
Products/Silva/Folder/views.py
