Metadata-Version: 1.1
Name: Products.Silva
Version: 3.0.4
Summary: Silva Content Management System
Home-page: https://github.com/silvacms/Products.Silva
Author: Infrae
Author-email: info@infrae.com
License: BSD
Keywords: silva cms zope
Platform: UNKNOWN
Classifier: Framework :: Zope2
Classifier: License :: OSI Approved :: BSD License
Classifier: Topic :: Internet :: WWW/HTTP :: Dynamic Content
Classifier: Programming Language :: Python
Classifier: Topic :: Software Development :: Libraries :: Python Modules
